setup.py
twitter_apponly_auth/__init__.py
twitter_apponly_auth/client.py
twitter_apponly_auth/exceptions.py
twitter_apponly_auth/models.py
twitter_apponly_auth.egg-info/PKG-INFO
twitter_apponly_auth.egg-info/SOURCES.txt
twitter_apponly_auth.egg-info/dependency_links.txt
twitter_apponly_auth.egg-info/requires.txt
twitter_apponly_auth.egg-info/top_level.txt