Metadata-Version: 1.0
Name: twitter-apponly-auth
Version: 0.0.1
Summary: An API Client for Twitter's Application Only Authentication
Home-page: UNKNOWN
Author: Joel Taddei / @taddeimania
Author-email: jtaddei@gmail.com
License: UNKNOWN
Platform: UNKNOWN
